alpyro_msgs/__init__.py
alpyro_msgs/_msg.py
alpyro_msgs/py.typed
alpyro_msgs/actionlib/__init__.py
alpyro_msgs/actionlib/testaction.py
alpyro_msgs/actionlib/testactionfeedback.py
alpyro_msgs/actionlib/testactiongoal.py
alpyro_msgs/actionlib/testactionresult.py
alpyro_msgs/actionlib/testfeedback.py
alpyro_msgs/actionlib/testgoal.py
alpyro_msgs/actionlib/testrequestaction.py
alpyro_msgs/actionlib/testrequestactionfeedback.py
alpyro_msgs/actionlib/testrequestactiongoal.py
alpyro_msgs/actionlib/testrequestactionresult.py
alpyro_msgs/actionlib/testrequestfeedback.py
alpyro_msgs/actionlib/testrequestgoal.py
alpyro_msgs/actionlib/testrequestresult.py
alpyro_msgs/actionlib/testresult.py
alpyro_msgs/actionlib/twointsaction.py
alpyro_msgs/actionlib/twointsactionfeedback.py
alpyro_msgs/actionlib/twointsactiongoal.py
alpyro_msgs/actionlib/twointsactionresult.py
alpyro_msgs/actionlib/twointsfeedback.py
alpyro_msgs/actionlib/twointsgoal.py
alpyro_msgs/actionlib/twointsresult.py
alpyro_msgs/actionlib_msgs/__init__.py
alpyro_msgs/actionlib_msgs/goalid.py
alpyro_msgs/actionlib_msgs/goalstatus.py
alpyro_msgs/actionlib_msgs/goalstatusarray.py
alpyro_msgs/actionlib_tutorials/__init__.py
alpyro_msgs/actionlib_tutorials/averagingaction.py
alpyro_msgs/actionlib_tutorials/averagingactionfeedback.py
alpyro_msgs/actionlib_tutorials/averagingactiongoal.py
alpyro_msgs/actionlib_tutorials/averagingactionresult.py
alpyro_msgs/actionlib_tutorials/averagingfeedback.py
alpyro_msgs/actionlib_tutorials/averaginggoal.py
alpyro_msgs/actionlib_tutorials/averagingresult.py
alpyro_msgs/actionlib_tutorials/fibonacciaction.py
alpyro_msgs/actionlib_tutorials/fibonacciactionfeedback.py
alpyro_msgs/actionlib_tutorials/fibonacciactiongoal.py
alpyro_msgs/actionlib_tutorials/fibonacciactionresult.py
alpyro_msgs/actionlib_tutorials/fibonaccifeedback.py
alpyro_msgs/actionlib_tutorials/fibonaccigoal.py
alpyro_msgs/actionlib_tutorials/fibonacciresult.py
alpyro_msgs/bond/__init__.py
alpyro_msgs/bond/constants.py
alpyro_msgs-0.1.0.dist-info/LICENSE
alpyro_msgs-0.1.0.dist-info/METADATA
alpyro_msgs-0.1.0.dist-info/WHEEL
alpyro_msgs-0.1.0.dist-info/top_level.txt
alpyro_msgs-0.1.0.dist-info/RECORD
