Metadata-Version: 2.1
Name: alpyro-msgs
Version: 0.1.0
Summary: Message definitions for alpyro
Home-page: https://github.com/rho2/alpyro_msgs
Author: Robin Brase
Author-email: git@rho2.eu
License: MIT
Platform: UNKNOWN
Classifier: License :: OSI Approved :: MIT License
Classifier: Intended Audience :: Developers
Classifier: Programming Language :: Python :: 3
Classifier: Programming Language :: Python :: 3 :: Only
Classifier: Programming Language :: Python :: 3.8
Requires-Python: >=3.8
Requires-Dist: typing-extensions (>=3.7.4.2)
